README.rst
setup.py
django_mailer_server_backend.egg-info/PKG-INFO
django_mailer_server_backend.egg-info/SOURCES.txt
django_mailer_server_backend.egg-info/dependency_links.txt
django_mailer_server_backend.egg-info/not-zip-safe
django_mailer_server_backend.egg-info/requires.txt
django_mailer_server_backend.egg-info/top_level.txt
mailer_server_backend/__init__.py