Metadata-Version: 1.1
Name: django-mailer-server-backend
Version: 0.1.4
Summary: A django mail backend for mailer server (https://github.com/spapas/mailer_server)
Home-page: https://github.com/spapas/django-mailer-server-backend
Author: Serafeim Papastefanos
Author-email: spapas@gmail.com
License: MIT
Platform: UNKNOWN
Classifier: Environment :: Web Environment
Classifier: Programming Language :: Python
Classifier: Programming Language :: Python :: 2
Classifier: Programming Language :: Python :: 2.7
Classifier: Programming Language :: Python :: 3
Classifier: Programming Language :: Python :: 3.6
Classifier: Framework :: Django
Classifier: Framework :: Django :: 2.0
Classifier: Intended Audience :: Developers
Classifier: License :: OSI Approved :: MIT License
Classifier: Operating System :: OS Independent
Classifier: Topic :: Internet :: WWW/HTTP
Classifier: Topic :: Software Development :: Libraries
